Workbook
Name Above400M: #REF!
Name Baseline: #REF!
Name Below400M: #REF!
Name Contract: #REF!
Name Distributor: #REF!
Name Entity: #REF!
Name Final: #REF!
Name Foreign: #REF!
Name Level: #REF!
Name LevelSelection: #REF!
Name ListTypes: #REF!
Name NoContract: #REF!
Name Other: #REF!
Name Periodic: #REF!
Name Producer: #REF!
Name Product: #REF!
Name Provider: #REF!
Name Purpose: #REF!
Name PurposeSelection: #REF!
Name ScenarioLabelIDs: #REF!
Name ScenarioLabels: #REF!
Name Supplementary: #REF!
Name Supplier: #REF!
Name SupplierTypes: #REF!
Name Target: #REF!
Name Value: #REF!
Name ValueSelection: #REF!

Sheet Overview
E1: Periodic or Final Report Template (at Contract Level) Local Content and Government Procurement Authority Template (N.3.2)
P3: Template Code | Q3: OM-LRF-08
P4: Version Number | Q4: V.2
B7: Overview | O7: Format
B8: The Local Content Template is provided by the Local Content and Government Procurement Authority to allow the entity to measure its contribution to Local Content. This Template provides a unified tool for reporting Local Content Score.
P9: ABC | Q9: Heading of the table
P10: ABC | Q10: Heading of the column or row
P11: ABC | Q11: Formula or pre-filled data
P12: ABC | Q12: Data to be filled by the Entity
B16: Contents | F16: Description
B17: Section 1. General Information | F17: General information about the entity and the types of products and services it provides
B18: Section 2. Evaluation | F18: Calculation and evaluation of the Local Content score for the entity
B19: Section 3. Labor | F19: The Entity's relevant expenses on labor compensation related to the contract execution during the reporting period
B20: Section 4. Goods & Services | F20: The Entity's relevant Goods and Services expenses related to the contract execution during the reporting period
B21: Section 5. Capacity Building | F21: The Entity's relevant expenses on KSA capacity building related to the contract execution during the reporting period
B22: Section 6. Depreciation and Amortization | F22: The Entity's depreciation and amortization related to the contract execution during the reporting period
B23: Appendix A. | F23: Local content scores for Goods and Services sectors
B25: *This document was originally prepared in Arabic, and the Arabic version should prevail.

Sheet Section 1. General Information
B1: Section 1: General Information | Y1: Periodic Report
B2: 1.1 Tender Information | Y2: Final Report
B3: Project Owner | Y3: First Report
B4: Tender Name | Y4: Second Report
B5: Tender/ Contract No. | Y5: Third Report
B6: Contract Start Date (DD/MM/YYYY) | Y6: Fourth Report
B7: Contract End Date (DD/MM/YYYY) | Y7: Fifth Report
B8: Contract Value | Y8: Sixth Report
B9: Report Type | I9: Periodic | Y9: Seventh Report
B10: Report Number | I10: Final | Y10: Eighth Report
Y11: Ninth Report
B12: 1.2 Entity Information | Y12: Tenth Report
B13: Full Name
B14: Main Address
B15: Start of Reporting Period (DD/MM/YYYY)1
B16: End of Reporting Period (DD/MM/YYYY)1
B17: KSA Unified National Number2
B19: 1.3 Contact person
B20: Full Name
B21: E-mail Address
B22: Office Phone Number
B23: Mobile Phone Number
B25: 1.4 Entity Description
B26: Please provide a brief description of the types of goods and services provided by the entity
... B29: 2. The entity's Unified National Number, if it is not available, enter the License Number, or please enter “Not applicable” to indicate that it does not have a unified national number or a license number in the Kingdom of Saudi Arabia.

Sheet Section 2. Evaluation
B1: Section 2: Evaluation of Local Content
B2: Tender Information
B3: Entity Name | C3: =IF('Section 1. General Information'!$C$13:$D$13="","",'Section 1. General Information'!$C$13:$D$13)
B4: Tender Name | C4: =IF('Section 1. General Information'!$C$4:$D$4="","",'Section 1. General Information'!$C$4:$D$4)
B5: Contract Start Date (DD/MM/YYYY) | C5: =IF('Section 1. General Information'!$C$6:$D$6="","",'Section 1. General Information'!$C$6:$D$6)
B6: Contract End Date (DD/MM/YYYY) | C6: =IF('Section 1. General Information'!$C$7:$D$7="","",'Section 1. General Information'!$C$7:$D$7)
B7: Contract Value | C7: =IF('Section 1. General Information'!$C$8="","",'Section 1. General Information'!$C$8)
B9: 2.1 Local Content Score1
B10: Evaluation Criteria | C10: Contribution to Local Content (SAR)
B11: Local Content from depreciation and amortization | C11: ='Section 6. Depreciation & Amor.'!F30 -> 0
B12: Local Content from labor | C12: ='Section 3. Labor'!E13 -> 0
B13: Local Content from Goods and Services | C13: ='Section 4. Goods and Services'!F11 -> 0
B14: Local Content from Saudi training | C14: ='Section 5. Capacity Building'!C10 -> 0
B15: Local Content from Supplier development | C15: ='Section 5. Capacity Building'!C13 -> 0
B16: Local Content from research and development | C16: ='Section 5. Capacity Building'!C16 -> 0
B17: Total Local Content Contribution for the Reporting Period | C17: =SUM(C11:E16) -> 0
B18: Total Relevant Cost of the Contract for the Reporting Period2 | C18: ='Section 3. Labor'!E11+'Section 4. Goods and Services'!F10+'Section 5. Capacity Building'!C10+'Section 5. Capacity Building'!C13+'Section 5. Capacity Building'!C16+'Section 6. Depreciation & Amor.'!C10 -> 0
B19: Local Content Score (%) | C19: =IFERROR(C17/C18,0) -> 0
B21: 2.2 Evaluation of the Local Content of the Prior Reports3
B22: Prior Reports (Does not include the current report) | C22: Total Local Content Contribution | D22: Total Relevant Cost of the Contract
B23: First Report | C23: 0 | D23: 0
B24: Second Report | C24: 0 | D24: 0
B25: Third Report | C25: 0 | D25: 0
B26: Forth Report | C26: 0 | D26: 0
B27: Fifth Report | C27: 0 | D27: 0
B28: Sixth Report | C28: 0 | D28: 0
B29: Seventh Report | C29: 0 | D29: 0
B30: Eighth Report | C30: 0 | D30: 0
B31: Ninth Report | C31: 0 | D31: 0
B32: Tenth Report | C32: 0 | D32: 0
B34: 2.3 Final Local Content Score of the Report
B35: Total Cumulative Contribution | C35: =SUM($C$23:$C$32,$C$17) -> 0
B36: Total Cumulative Relevant Costs | C36: =SUM($D$23:$D$32,$C$18) -> 0
B37: Cumulative Local Content Score % | C37: =IFERROR(C35/C36,0) -> 0
B40: 1. The local content score shows the actual value contributed by the entity related to the contract during the reporting period.
B41: 2. The total cost related to the contract during the reporting period for operational activities including employee compensation, goods and services, capacity building, and depreciation and amortization of assets.
B42: 3. The total relevant cost and the total local content contribution for the prior reports related to the contract.

Sheet Section 3. Labor
B1: Section 3: Labor
B2: Tender Information
B3: Entity Name | C3: =IF('Section 1. General Information'!$C$13:$D$13="","",'Section 1. General Information'!$C$13:$D$13)
B4: Tender Name | C4: =IF('Section 1. General Information'!$C$4:$D$4="","",'Section 1. General Information'!$C$4:$D$4)
B5: Contract Start Date (DD/MM/YYYY) | C5: =IF('Section 1. General Information'!$C$6:$D$6="","",'Section 1. General Information'!$C$6:$D$6)
B6: Contract End Date (DD/MM/YYYY) | C6: =IF('Section 1. General Information'!$C$7:$D$7="","",'Section 1. General Information'!$C$7:$D$7)
B7: Contract Value | C7: =IF('Section 1. General Information'!$C$8="","",'Section 1. General Information'!$C$8)
B9: 3.1 Labor Compensations Related to Contract Execution during the Reporting Period1
C10: Compensation of Saudi employees (SAR)3 | D10: Compensation of foreign employees (SAR) | E10: Total compensation (SAR)
B11: Total compensation (SAR)2 | C11: 0 | D11: 0 | E11: =SUM(C11:D11) -> 0
B12: Contribution to Local Content (%) | C12: 1 | D12: 0.534 | E12: =IFERROR(E13/E11,0) -> 0
B13: Contribution to Local Content (SAR) | C13: =C11*C12 -> 0 | D13: =D11*D12 -> 0 | E13: =SUM(C13:D13) -> 0
B15: 3.2 Average count of the employees for the Reported Financial Year
C16: Saudi Employees3 | D16: Foreign Employees | E16: Total
B17: Average count of Male Employees | C17: 0 | D17: 0 | E17: =SUM(C17:D17) -> 0
B18: Average count of Femal Employees | C18: 0 | D18: 0 | E18: =SUM(C18:D18) -> 0
B19: Average Employees Count | C19: =SUM(C17:C18) -> 0 | D19: =SUM(D17:D18) -> 0 | E19: =SUM(E17:E18) -> 0
B21: 1. Compensation of Saudi and foreign employees of the entity in the Kingdom of Saudi Arabia related to the contract execution during the reporting period, excluding the training expenses of Saudis included in Section 5 “Capacity Building”.
B22: 2. Employees compensations includes salaries, wages, bonuses and benefits (e.g.: commissions, overtime, transportation allowances, housing allowances, vacations, other allowances, end-of-service benefits provision, and General Organization for Social Insurance (“GOSI”) contributions).
B23: 3. A Saudi employee is any person who holds Saudi nationality or who is legally treated as a Saudi.

Sheet Section 4. Goods and Services
B1: Section 4: Goods and Services
B2: Tender Information
B3: Entity Name | C3: =IF('Section 1. General Information'!$C$13:$D$13="","",'Section 1. General Information'!$C$13:$D$13)
B4: Tender Name | C4: =IF('Section 1. General Information'!$C$4:$D$4="","",'Section 1. General Information'!$C$4:$D$4)
B5: Contract Start Date (DD/MM/YYYY) | C5: =IF('Section 1. General Information'!$C$6:$D$6="","",'Section 1. General Information'!$C$6:$D$6)
B6: Contract End Date (DD/MM/YYYY) | C6: =IF('Section 1. General Information'!$C$7:$D$7="","",'Section 1. General Information'!$C$7:$D$7)
B7: Contract Value | C7: =IF('Section 1. General Information'!$C$8="","",'Section 1. General Information'!$C$8)
B9: 4.1 Total Expenses Related to Contract Execution for the Reporting Period
B10: Total Expenses of Goods and Services (SAR)1 | F10: 0
B11: Contribution to Local Content from Goods and Services (SAR) | F11: =O57 -> 0
B13: 4.2 Expense on Goods and Services Related to Contract Execution for the Reporting Period
B14: Full name2,3 | E14: Unified National Number or KSA Commercial registration number4 | F14: Brief description of the goods or services provided | G14: Goods/Services | H14: Local/Foreign | I14: Factory Manufactored the supplied good, and Unified National Number -if Available-5 | J14: Sector of the goods or services procured from the supplier | K14: Audited Score (%), If applicable6 | L14: Sector Score (%) | M14: Selected Score (%) | N14: Total Expenses (SAR)7 | O14: Local Content Contribution (SAR)
A15: 1 | L15: =IFERROR(INDEX('Appendix A'!$C$5:$C$42,MATCH('Section 4. Goods and Services'!J15,'Appendix A'!$B$5:$B$42,0)),0) -> 0 | M15: =IF(K15<=0,L15,K15) -> 0 | N15: 0 | O15: =N15*M15 -> 0 | P15: =IF(O15>1%*'Section 2. Evaluation'!$C$18,"To be confirmed","")
A16: =A15+1 -> 2 | L16: =IFERROR(INDEX('Appendix A'!$C$5:$C$42,MATCH('Section 4. Goods and Services'!J16,'Appendix A'!$B$5:$B$42,0)),0) -> 0 | M16: =IF(K16<=0,L16,K16) -> 0 | N16: 0 | O16: =N16*M16 -> 0 | P16: =IF(O16>1%*'Section 2. Evaluation'!$C$18,"To be confirmed","")
A17: =A16+1 -> 3 | L17: =IFERROR(INDEX('Appendix A'!$C$5:$C$42,MATCH('Section 4. Goods and Services'!J17,'Appendix A'!$B$5:$B$42,0)),0) -> 0 | M17: =IF(K17<=0,L17,K17) -> 0 | N17: 0 | O17: =N17*M17 -> 0 | P17: =IF(O17>1%*'Section 2. Evaluation'!$C$18,"To be confirmed","")
A18: =A17+1 -> 4 | L18: =IFERROR(INDEX('Appendix A'!$C$5:$C$42,MATCH('Section 4. Goods and Services'!J18,'Appendix A'!$B$5:$B$42,0)),0) -> 0 | M18: =IF(K18<=0,L18,K18) -> 0 | N18: 0 | O18: =N18*M18 -> 0 | P18: =IF(O18>1%*'Section 2. Evaluation'!$C$18,"To be confirmed","")
A19: =A18+1 -> 5 | L19: =IFERROR(INDEX('Appendix A'!$C$5:$C$42,MATCH('Section 4. Goods and Services'!J19,'Appendix A'!$B$5:$B$42,0)),0) -> 0 | M19: =IF(K19<=0,L19,K19) -> 0 | N19: 0 | O19: =N19*M19 -> 0 | P19: =IF(O19>1%*'Section 2. Evaluation'!$C$18,"To be confirmed","")
A20: =A19+1 -> 6 | L20: =IFERROR(INDEX('Appendix A'!$C$5:$C$42,MATCH('Section 4. Goods and Services'!J20,'Appendix A'!$B$5:$B$42,0)),0) -> 0 | M20: =IF(K20<=0,L20,K20) -> 0 | N20: 0 | O20: =N20*M20 -> 0 | P20: =IF(O20>1%*'Section 2. Evaluation'!$C$18,"To be confirmed","")
A21: =A20+1 -> 7 | L21: =IFERROR(INDEX('Appendix A'!$C$5:$C$42,MATCH('Section 4. Goods and Services'!J21,'Appendix A'!$B$5:$B$42,0)),0) -> 0 | M21: =IF(K21<=0,L21,K21) -> 0 | N21: 0 | O21: =N21*M21 -> 0 | P21: =IF(O21>1%*'Section 2. Evaluation'!$C$18,"To be confirmed","")
A22: =A21+1 -> 8 | L22: =IFERROR(INDEX('Appendix A'!$C$5:$C$42,MATCH('Section 4. Goods and Services'!J22,'Appendix A'!$B$5:$B$42,0)),0) -> 0 | M22: =IF(K22<=0,L22,K22) -> 0 | N22: 0 | O22: =N22*M22 -> 0 | P22: =IF(O22>1%*'Section 2. Evaluation'!$C$18,"To be confirmed","")
A23: =A22+1 -> 9 | L23: =IFERROR(INDEX('Appendix A'!$C$5:$C$42,MATCH('Section 4. Goods and Services'!J23,'Appendix A'!$B$5:$B$42,0)),0) -> 0 | M23: =IF(K23<=0,L23,K23) -> 0 | N23: 0 | O23: =N23*M23 -> 0 | P23: =IF(O23>1%*'Section 2. Evaluation'!$C$18,"To be confirmed","")
A24: =A23+1 -> 10 | L24: =IFERROR(INDEX('Appendix A'!$C$5:$C$42,MATCH('Section 4. Goods and Services'!J24,'Appendix A'!$B$5:$B$42,0)),0) -> 0 | M24: =IF(K24<=0,L24,K24) -> 0 | N24: 0 | O24: =N24*M24 -> 0 | P24: =IF(O24>1%*'Section 2. Evaluation'!$C$18,"To be confirmed","")
A25: =A24+1 -> 11 | L25: =IFERROR(INDEX('Appendix A'!$C$5:$C$42,MATCH('Section 4. Goods and Services'!J25,'Appendix A'!$B$5:$B$42,0)),0) -> 0 | M25: =IF(K25<=0,L25,K25) -> 0 | N25: 0 | O25: =N25*M25 -> 0 | P25: =IF(O25>1%*'Section 2. Evaluation'!$C$18,"To be confirmed","")
A26: =A25+1 -> 12 | L26: =IFERROR(INDEX('Appendix A'!$C$5:$C$42,MATCH('Section 4. Goods and Services'!J26,'Appendix A'!$B$5:$B$42,0)),0) -> 0 | M26: =IF(K26<=0,L26,K26) -> 0 | N26: 0 | O26: =N26*M26 -> 0 | P26: =IF(O26>1%*'Section 2. Evaluation'!$C$18,"To be confirmed","")
A27: =A26+1 -> 13 | L27: =IFERROR(INDEX('Appendix A'!$C$5:$C$42,MATCH('Section 4. Goods and Services'!J27,'Appendix A'!$B$5:$B$42,0)),0) -> 0 | M27: =IF(K27<=0,L27,K27) -> 0 | N27: 0 | O27: =N27*M27 -> 0 | P27: =IF(O27>1%*'Section 2. Evaluation'!$C$18,"To be confirmed","")
... A54: =A53+1 -> 40 | L54: =IFERROR(INDEX('Appendix A'!$C$5:$C$42,MATCH('Section 4. Goods and Services'!J54,'Appendix A'!$B$5:$B$42,0)),0) -> 0 | M54: =IF(K54<=0,L54,K54) -> 0 | N54: 0 | O54: =N54*M54 -> 0 | P54: =IF(O54>1%*'Section 2. Evaluation'!$C$18,"To be confirmed","")
B55: Other Disallowable Costs (unallocated cost) | M55: 0 | N55: 0 | O55: =M55*N55 -> 0
B56: Remaining expenses (SAR) | M56: =IFERROR(SUMPRODUCT($N$15:$N$55,$M$15:$M$55)/SUM($N$15:$N$55),0) -> 0 | N56: =F10-SUM(N15:N55) -> 0 | O56: =N56*M56 -> 0
B57: Total expenses (SAR) | N57: =SUM(N15:N56) -> 0 | O57: =SUM(O15:O56) -> 0
B58: Has the required percentage or number of suppliers been covered? | N58: =IFERROR(IF(F10<=0,"",IF(OR(AND(N56=0,F10>0),COUNTIFS($N$15:$N$54,">"&0)>=10),IF((SUM(N15:N55)/F10)>=70%,"Yes","No"),"No")),"")
B60: 1. Includes the operating expenses and overhead costs of the entity on goods and services related to contract execution during the reporting period.
B61: 2. List at least 70% or top 40 suppliers of the total expenses on Goods and Services in descending order by cost. The entity should contact LCGPA, in order to list more than 40 suppliers.
B62: 3. Supplier's commercial registration number in the Kingdom of Saudi Arabia, and if it is not available, please enter the license number or “not applicable” to indicate that the supplier does not have a commercial registration or license number in the Kingdom of Saudi Arabia.
B63: 4. Enter the supplier's latest audited score or use the sector score of the consumed goods or services.
B64: 5. Total expenses refer to the value of total purchases, consumed materials or provided services from suppliers -individually- by the entity related to contract execution during the reporting period, as per the Guidelines and related instructions.

Sheet Section 5. Capacity Building
B1: Section 5: Capacity Building
B2: Tender Information
B3: Entity Name | C3: =IF('Section 1. General Information'!$C$13:$D$13="","",'Section 1. General Information'!$C$13:$D$13)
B4: Tender Name | C4: =IF('Section 1. General Information'!$C$4:$D$4="","",'Section 1. General Information'!$C$4:$D$4)
B5: Contract Start Date (DD/MM/YYYY) | C5: =IF('Section 1. General Information'!$C$6:$D$6="","",'Section 1. General Information'!$C$6:$D$6)
B6: Contract End Date (DD/MM/YYYY) | C6: =IF('Section 1. General Information'!$C$7:$D$7="","",'Section 1. General Information'!$C$7:$D$7)
B7: Contract Value | C7: =IF('Section 1. General Information'!$C$8="","",'Section 1. General Information'!$C$8)
B9: 5.1 Expenses on Training of Saudis
B10: Expenses related to contract execution during the reporting period (SAR)1 | C10: 0
B12: 5.2 Expenses on KSA Suppliers Development
B13: Expenses related to contract execution during the reporting period (SAR)2 | C13: 0
B15: 5.3 Expenses on KSA Research and Development
B16: Expenses related to contract execution during the reporting period (SAR)3 | C16: 0
B18: 1. Expenses on the training of Saudi employees related to contract execution during the reporting period, this includes the cost of trainees and scholarships. Note that the expenses of this section shall not be repeated with other key performance indicators.
B19: 2. Expenses on the development of suppliers (who have a Saudi commercial registration number or license number in KSA) related to contract execution during the reporting period, through training and contribution to enhance suppliers' capabilities. Note that the expenses of this section shall not be repeated with other key performance indicators.
B20: 3. Expenses on research and development activities in KSA related to contract execution during the reporting period. Note that the expenses of this section shall not be repeated with other key performance indicators.

Sheet Section 6. Depreciation & Amor.
B1: Section 6: Depreciation and Amortization
B2: Contract Information
B3: Entity Name | C3: =IF('Section 1. General Information'!$C$13:$D$13="","",'Section 1. General Information'!$C$13:$D$13)
B4: Tender Name | C4: =IF('Section 1. General Information'!$C$4:$D$4="","",'Section 1. General Information'!$C$4:$D$4)
B5: Contract Start Date (DD/MM/YYYY) | C5: =IF('Section 1. General Information'!$C$6:$D$6="","",'Section 1. General Information'!$C$6:$D$6)
B6: Contract End Date (DD/MM/YYYY) | C6: =IF('Section 1. General Information'!$C$7:$D$7="","",'Section 1. General Information'!$C$7:$D$7)
B7: Contract Value | C7: =IF('Section 1. General Information'!$C$8="","",'Section 1. General Information'!$C$8)
B9: 6.1 Depreciation and Amortization of Assets in the Kingdom of Saudi Arabia
B10: Total depreciation and amortization (SAR) | C10: 0
B11: Contribution to Local Content (SAR) | C11: =F30 -> 0
B12: Local Content Score (%) | C12: =IFERROR(C11/C10,0) -> 0
B14: 6.2 Depreciation and Amortization by Asset class in the Kingdom of Saudi Arabia
B15: Asset Class | C15: Examples of Assets in Productive Asset class | D15: Local Assets | E15: Foreign Assets | F15: Local Content contribution (SAR)1
D16: Depreciation/Amortization (SAR) | E16: Depreciation/Amortization (SAR)
A17: 1 | B17: Building and Land Improvements2 | C17: Buildings / Land and Building Improvements | D17: 0 | F17: =D17*100% -> 0
A18: =A17+1 -> 2 | B18: Furniture and Fixtures | C18: Office furniture, desks, cubicles, office chairs | D18: 0 | E18: 0 | F18: =(D18*100%)+(E18*30%) -> 0 | G18: =IF(D18>1%*'Section 2. Evaluation'!$C$18,"Need to be tested","")
A19: =A18+1 -> 3 | B19: Machinery and Equipment | C19: Industrial equipment, testing equipment, information and communication technology equipment | D19: 0 | E19: 0 | F19: =(D19*100%)+(E19*30%) -> 0 | G19: =IF(D19>1%*'Section 2. Evaluation'!$C$18,"Need to be tested","")
A20: =A19+1 -> 4 | B20: Vehicles | C20: Mobile cranes, Trucks, vans, cars, trailers, fork lifts | D20: 0 | E20: 0 | F20: =(D20*100%)+(E20*30%) -> 0 | G20: =IF(D20>1%*'Section 2. Evaluation'!$C$18,"Need to be tested","")
A21: =A20+1 -> 5 | B21: Infrastructure | C21: Infrastructure works such as road networks, energy, and water | D21: 0 | E21: 0 | F21: =(D21*100%)+(E21*30%) -> 0 | G21: =IF(D21>1%*'Section 2. Evaluation'!$C$18,"Need to be tested","")
A22: =A21+1 -> 6 | B22: Investment properties | C22: Real estate assets such as residential buildings and commercial buildings | D22: 0 | E22: 0 | F22: =(D22*100%)+(E22*30%) -> 0 | G22: =IF(D22>1%*'Section 2. Evaluation'!$C$18,"Need to be tested","")
A23: =A22+1 -> 7 | B23: Right-of-Use for leases, machinery, equipment, and vehicles | C23: Lease agreements for buildings, equipment, and vehicles | D23: 0 | E23: 0 | F23: =(D23*100%)+(E23*30%) -> 0 | G23: =IF(D23>1%*'Section 2. Evaluation'!$C$18,"Need to be tested","")
A24: =A23+1 -> 8 | B24: Right-of-Use for Systems and Applications | C24: License to use computer software, systems | D24: 0 | E24: 0 | F24: =(D24*100%)+(E24*30%) -> 0 | G24: =IF(D24>1%*'Section 2. Evaluation'!$C$18,"Need to be tested","")
A25: =A24+1 -> 9 | B25: Other (Please describe) | C25: Other (please give examples) | D25: 0 | E25: 0 | F25: =(D25*100%)+(E25*30%) -> 0 | G25: =IF(D25>1%*'Section 2. Evaluation'!$C$18,"Need to be tested","")
A26: =A25+1 -> 10 | B26: Other (Please describe) | C26: Other (please give examples) | D26: 0 | E26: 0 | F26: =(D26*100%)+(E26*30%) -> 0 | G26: =IF(D26>1%*'Section 2. Evaluation'!$C$18,"Need to be tested","")
A27: =A26+1 -> 11 | B27: Other (Please describe) | C27: Other (please give examples) | D27: 0 | E27: 0 | F27: =(D27*100%)+(E27*30%) -> 0 | G27: =IF(D27>1%*'Section 2. Evaluation'!$C$18,"Need to be tested","")
A28: =A27+1 -> 12 | B28: Other (Please describe) | C28: Other (please give examples) | D28: 0 | E28: 0 | F28: =(D28*100%)+(E28*30%) -> 0 | G28: =IF(D28>1%*'Section 2. Evaluation'!$C$18,"Need to be tested","")
A29: =A28+1 -> 13 | B29: Other (Please describe) | C29: Other (please give examples) | D29: 0 | E29: 0 | F29: =(D29*100%)+(E29*30%) -> 0 | G29: =IF(D29>1%*'Section 2. Evaluation'!$C$18,"Need to be tested","")
B30: Total depreciation and amortization | D30: =SUM(D17:D29) -> 0 | E30: =SUM(E18:E29) -> 0 | F30: =SUM(F17:F29) -> 0
B32: 1. Local Content Score for assets manufactured in the KSA, and 30% for assets manufactured outside KSA.
B33: 2. All depreciataion related to this category is considered 100% local content as long as they are located in KSA.

Sheet Appendix A
B1: Appendix A
B2: A.1 List of Sector Local Content Scores
B3: General information on Sector Local Content Scores
B4: Sector | C4: Local Content Score (%) | D4: Description | E4: ISIC Code
B5: 1_SERVICES - KSA Accommodation and Facility Rental | C5: 0.6 | D5: The procurement of Services for short-term accommodation (e.g. Hotels) Camping grounds, Other accommodation (e.g. student residences) and rental of office buildings, compounds, warehouses, etc. | E5: 55, 68102
B6: 2_SERVICES - KSA Food and Beverages | C6: 0.4 | D6: The procurement of Services for food and beverages (e.g. Restaurants, catering; the purchase of ready-made food & beverage products is not included) | E6: 56
B7: 3_SERVICES - KSA Industrial Services | C7: 0.36 | D7: The procurement of testing, inspection, certification, calibration, maintenance, blasting, painting, coating and galvanizing services, steam and air conditioning supply | E7: 25921, 33, 35, Exc. 351&352, 38 Exc.381103&383, 712
B8: 4_SERVICES - KSA Security Services | C8: 0.82 | D8: The procurement of security services including guard and patrol services (e.g. Security of facilities) and armored car services, operation of electronic security alarm systems (e.g. fire alarm) | E8: 80, 811001
B9: 5_SERVICES - KSA local Professional Services | C9: 0.5 | D9: The procurement of Professional consulting, Such as engineering, accounting, legal, management consultancy (e.g. strategic, financial planning, budgeting, marketing, policies, HR) | E9: 69-74 Exc. 712
B10: 6_SERVICES - KSA local representative of Foreign professional service provider | C10: 0.2 | D10: The procurement of Professional consulting, Such as engineering, accounting, legal, management consultancy (e.g. strategic, financial planning, budgeting, marketing, policies, HR) provided by a local representative of foreign professional service provider | E10: 69-74 Exc. 712
B11: 7_SERVICES - KSA Real Estate | C11: 0.48 | D11: The procurement of services for selling or buying real estate, providing other real estate services such as appraising real estate or acting as real estate escrow agents. Exc. Facility rental | E11: 68 Exc.68102
B12: 8_SERVICES - KSA Construction | C12: 0.4 | D12: The procurement of construction Services, specialized construction activities for buildings and civil engineering works (e.g., contracting; the procurement of pure construction materials is categorized under Goods sectors), interior and exterior painting of buildings | E12: 41-43
B13: 9_SERVICES - KSA Education | C13: 0.66 | D13: The procurement of all education activities for any profession, oral or written as well as by radio and television or other means of communication (e.g., professional training, language education) | E13: 75, 85
B14: 10_SERVICES - KSA Finance and Insurance | C14: 0.75 | D14: The procurement of all financial Services (e.g., banking, funds management); this category also includes the procurement of insurance and pension Services (e.g., health insurance, transport insurance, accident and fire insurance) | E14: 64-66
B15: 11_SERVICES - KSA Healthcare | C15: 0.38 | D15: The procurement of all Services related to healthcare (the procurement of healthcare equipment and pharmaceuticals is categorized under Goods sectors) | E15: 86-88
B16: 12_SERVICES - KSA Public Administration and Defence | C16: 0.69 | D16: The procurement of Services produced by government bodies (General public administration activities, Foreign affairs, Defence activities, etc) | E16: 84
B17: 13_SERVICES - KSA Transport and Logistics | C17: 0.45 | D17: The procurement of transport and logistics services from locally based service providers. This sector includes shipping, transportation, cargo services and Saudi based airlines (including freight forward),(Foreign airlines booked by local agency is categorized under foreign service agent),Exc. Rental of cars | E17: 49-53 Exc.49225, 79-7911
B18: 14_SERVICES - KSA Onshore Drilling | C18: 0.3 | D18: The procurement of onshore drilling services | E18: 06, 091
... B30: 26_GOODS - KSA Chemicals & Oil and Gas | C30: 0.61 | D30: The procurement of locally produced chemicals, plastics, manufactured chemical Goods, and Oil & Gas product (e.g. Rubber). | E30: 19-20, 22, 352
B31: 27_GOODS - KSA Chemical Blending | C31: 0.29 | D31: The procurement of locally produced chemicals where the raw material is imported. This sector includes paint manufacturers | E31: 20
B32: 28_GOODS - KSA Machinery and Equipment | C32: 0.25 | D32: The procurement of locally produced machinery and equipment | E32: 265-268, 28 Exc.2813&2814, 29-30
B33: 29_GOODS - KSA Electrical Materials | C33: 0.4 | D33: The procurement of locally produced electrical materials including switch gears, junction boxes, trays, conduits, fixtures, inverters skid and other electrical materials, , Excluding PV panels and electrical inverters. | E33: 27, 2814
B34: 30_GOODS - KSA Mining | C34: 0.45 | D34: The procurement of locally produced raw materials extracted by the mining industry (e.g., coal, metal ores) | E34: 05, 07-08
B35: 31_GOODS - KSA Static Equipment | C35: 0.3 | D35: The procurement of locally produced static equipment such as tanks, pressure vessels and valves (control valves excluded) and steel manufacturers and structural | E35: 24-25 Exc.25114&25921, 2813
B36: 32_GOODS - KSA Cement and Gypsum | C36: 0.5 | D36: The procurement of locally produced cement, concrete and gypsum | E36: 2394-2395
B37: 33_GOODS - KSA Steel Rebar Manufacturing | C37: 0.6 | D37: The procurement of locally produced steel rebar | E37: 25114
B38: 34_GOODS - KSA IT & Telecom Manufacturing | C38: 0.15 | D38: The procurement of manufacturing of computer& electronic components, communication equipment (agents/resellers are not considered) | E38: 261-264
B39: 35_GOODS - KSA Other Manufacturing | C39: 0.3 | D39: The procurement of locally produced paper products, wood products, furniture, secondary raw material, textiles, pharmaceuticals and other industries, Including PV panels and electrical inverters. | E39: 13-18, 21, 23 Exc.2394&2395, 31-32 (Inc. 2790 PV panels and Electrical inverters)
B40: 36_GOODS - KSA Recyclers | C40: 0.7 | D40: The procurement of locally recycled metal scrap, paper, plastic and rubber | E40: 381103, 383
B41: 37_GOODS - KSA Agent or Distributor | C41: 0.05 | D41: The procurement of any kind of Goods from KSA Suppliers who do not produce these Goods; instead, distributors/ traders import and distribute these Goods | E41: 45-47
B42: 38_GOODS - Foreign | C42: 0 | D42: The procurement of Goods from foreign producers, i.e. entities without legal registration in KSA (direct Goods imports) | E42: N /A (supplier type)
