Workbook
Name Above400M: #REF!
Name Baseline: #REF!
Name Below400M: #REF!
Name Contract: #REF!
Name Distributor: #REF!
Name Entity: #REF!
Name Final: #REF!
Name Foreign: #REF!
Name Level: #REF!
Name LevelSelection: #REF!
Name ListTypes: #REF!
Name NoContract: #REF!
Name Other: #REF!
Name Periodic: #REF!
Name Producer: #REF!
Name Product: #REF!
Name Provider: #REF!
Name Purpose: #REF!
Name PurposeSelection: #REF!
Name ScenarioLabelIDs: #REF!
Name ScenarioLabels: #REF!
Name Supplementary: #REF!
Name Supplier: #REF!
Name SupplierTypes: #REF!
Name Target: #REF!
Name Value: #REF!
Name ValueSelection: #REF!

Sheet Overview
E2: Target Local Content Score Template (at Entity Level) Local Content and Government Procurement Authority
Q3: Template Code | R3: OM-LRF-10
Q4: Version Number | R4: V.1
B9: Overview | O9: Format
B10: The Local Content Template is provided by the Local Content and Government Procurement Authority to allow the entity to measure its contribution to Local Content. This Template provides a unified tool for reporting Local Content Score.
P11: ABC | Q11: Heading of the table
P12: ABC | Q12: Heading of the column or row
P13: ABC | Q13: Formula or pre-filled data
P14: ABC | Q14: Data to be filled by the Entity
B18: Contents | F18: Description
B19: Section 1. General Information | F19: General information about the entity and the types of products and services it provides
B20: Section 2. Evaluation | F20: Calculation and evaluation of the Local Content score for the entity
B21: Section 3. Labor | F21: The entity's relevant expenses on labor compensation for the financial year prior the end of the contract.
B22: Section 4. Goods & Services | F22: The entity's relevant Goods and Services expenses for the financial year prior the end of the contract.
B23: Section 5. Capacity Building | F23: The entity's relevant expenses on KSA capacity building for the financial year prior the end of the contract.
B24: Section 6. Depreciation and Amortization | F24: The entity's depreciation and amortization for the financial year prior the end of the contract.
B25: Appendix A. | F25: Local content scores for Goods and Services sectors
B27: *This document was originally prepared in Arabic, and the Arabic version should prevail.

Sheet Section 1. General Information
B1: Section 1: General Information
B2: 1.1 Tender Information
B3: Project Owner
B4: Tender Name
B5: Contract Start Date (DD/MM/YYYY)
B6: Contract End Date (DD/MM/YYYY)
B8: 1.2 Entity Information
B9: Full Name
B10: Main Address
B11: End of the Financial Year (DD/MM/YYYY)1
B12: KSA Commercial Registration Number2
B14: 1.3 Contact person
... B28: 3. Local Content is defined as the total spending on Saudi components within Labor, Goods & Services, Capacity Building, Assets, Technology and other elements within the Kingdom of Saudi Arabia.

Sheet Section 2. Evaluation
B1: Section 2: Evaluation of Target Local Content Score
B2: Tender Information
B3: Entity Name | C3: =IF('Section 1. General Information'!$C$9:$D$9="","",'Section 1. General Information'!$C$9:$D$9)
B4: ='Section 1. General Information'!$B$4 -> Tender Name | C4: =IF('Section 1. General Information'!$C$4:$D$4="","",'Section 1. General Information'!$C$4:$D$4)
B5: Contract Start Date (DD/MM/YYYY) | C5: =IF('Section 1. General Information'!$C$5:$D$5="","",'Section 1. General Information'!$C$5:$D$5)
B6: Contract End Date (DD/MM/YYYY) | C6: =IF('Section 1. General Information'!$C$6:$D$6="","",'Section 1. General Information'!$C$6:$D$6)
B8: 2.1 Target Local Content Score1
B9: Evaluation Criteria | C9: Contribution to Local Content (SAR)
B10: Local Content from depreciation and amortization | C10: ='Section 6. Depreciation & Amor.'!G25 -> 0
B11: Local Content from labor | C11: ='Section 3. Labor'!E12 -> 0
B12: Local Content from Goods and Services | C12: ='Section 4. Goods and Services'!F10 -> 0
B13: Local Content from Saudi training | C13: ='Section 5. Capacity Building'!C9 -> 0
B14: Local Content from Supplier development | C14: ='Section 5. Capacity Building'!C12 -> 0
B15: Local Content from research and development | C15: ='Section 5. Capacity Building'!C15 -> 0
B16: Total Local Content Contribution for the Reporting Period | C16: =SUM(C10:E15) -> 0
B17: Total Relevant Cost of the Contract for the Reporting Period2 | C17: ='Section 3. Labor'!E10+'Section 4. Goods and Services'!F9+'Section 5. Capacity Building'!C9+'Section 5. Capacity Building'!C12+'Section 5. Capacity Building'!C15+'Section 6. Depreciation & Amor.'!C9 -> 0
B18: Target Local Content Score (%) | C18: =IFERROR(IF(((C16/C17)+'Section 5. Capacity Building'!C17)>1,1,((C16/C17)+'Section 5. Capacity Building'!C17)),0) -> 0
B20: 1. The target local content score shows the value of the local content that the entity will contribute during the financial year prior the end of the contract.
B21: 2. The planned total cost during the financial year prior the end of the contract for operational activities including employee compensation, goods and services, capacity building, and depreciation and amortization of assets.

Sheet Section 3. Labor
B1: Section 3: Labor
B2: Tender information
B3: Entity Name | C3: =IF('Section 1. General Information'!$C$9:$D$9="","",'Section 1. General Information'!$C$9:$D$9)
B4: ='Section 1. General Information'!$B$4 -> Tender Name | C4: =IF('Section 1. General Information'!$C$4:$D$4="","",'Section 1. General Information'!$C$4:$D$4)
B5: Contract Start Date (DD/MM/YYYY) | C5: =IF('Section 1. General Information'!$C$5:$D$5="","",'Section 1. General Information'!$C$5:$D$5)
B6: Contract End Date (DD/MM/YYYY) | C6: =IF('Section 1. General Information'!$C$6:$D$6="","",'Section 1. General Information'!$C$6:$D$6)
B8: 3.1 Planned Labor Compensations during the Financial Year Prior the End of the Contract1
C9: Compensation of Saudi employees (SAR)3 | D9: Compensation of foreign employees (SAR) | E9: Total compensation (SAR)
B10: Total compensation (SAR)2 | C10: 0 | D10: 0 | E10: =SUM(C10:D10) -> 0
B11: Contribution to Local Content (%) | C11: 1 | D11: 0.534 | E11: =IFERROR(E12/E10,0) -> 0
B12: Contribution to Local Content (SAR) | C12: =C10*C11 -> 0 | D12: =D10*D11 -> 0 | E12: =SUM(C12:D12) -> 0
B14: 1. Planned compensation of Saudi and foreign employees of the entity in the Kingdom of Saudi Arabia during the financial year prior the end of the contract, excluding the training expenses of Saudis included in Section 5 “Capacity Building”.
B15: 2. Employees compensations includes salaries, wages, bonuses and benefits (e.g.: commissions, overtime, transportation allowances, housing allowances, vacations, other allowances, end-of-service benefits provision, and General Organization for Social Insurance (“GOSI”) contributions).
B16: 3. A Saudi employee is any person who holds Saudi nationality or who is legally treated as a Saudi.

Sheet Section 4. Goods and Services
B1: Section 4: Goods and Services
B2: Tender Information
B3: Entity Name | C3: =IF('Section 1. General Information'!$C$9:$D$9="","",'Section 1. General Information'!$C$9:$D$9)
B4: ='Section 1. General Information'!$B$4 -> Tender Name | C4: =IF('Section 1. General Information'!$C$4:$D$4="","",'Section 1. General Information'!$C$4:$D$4)
B5: Contract Start Date (DD/MM/YYYY) | C5: =IF('Section 1. General Information'!$C$5:$D$5="","",'Section 1. General Information'!$C$5:$D$5)
B6: Contract End Date (DD/MM/YYYY) | C6: =IF('Section 1. General Information'!$C$6:$D$6="","",'Section 1. General Information'!$C$6:$D$6)
B8: 4.1 Planned Total Expenses during the Financial Year Prior the End of the Contract
B9: Total expense of Goods and Services (SAR)1 | F9: 0
B10: Contribution to Local Content from Goods and Services (SAR) | F10: =N55 -> 0
B12: 4.2 Planned Expenses on Goods and Services during the Financial Year Prior the End of the Contract
B13: Full Name (If identified)2 | E13: KSA Commercial registration number (If identified)3 | F13: Brief description of the goods or services provided | G13: Goods/Services | H13: Local/Foreign | I13: Sector of the goods or services procured from the supplier | J13: Audited Score (%), If applicable4 | K13: Sector Score (%) | L13: Selected Score (%) | M13: Planned Total Expenses (SAR)5 | N13: Local Content Contribution (SAR)
A14: 1 | K14: =IFERROR(INDEX('Appendix A'!$C$5:$C$42,MATCH('Section 4. Goods and Services'!I14,'Appendix A'!$B$5:$B$42,0)),0) -> 0 | L14: =IF(J14<=0,K14,J14) -> 0 | M14: 0 | N14: =M14*L14 -> 0
A15: =A14+1 -> 2 | K15: =IFERROR(INDEX('Appendix A'!$C$5:$C$42,MATCH('Section 4. Goods and Services'!I15,'Appendix A'!$B$5:$B$42,0)),0) -> 0 | L15: =IF(J15<=0,K15,J15) -> 0 | M15: 0 | N15: =M15*L15 -> 0
A16: =A15+1 -> 3 | K16: =IFERROR(INDEX('Appendix A'!$C$5:$C$42,MATCH('Section 4. Goods and Services'!I16,'Appendix A'!$B$5:$B$42,0)),0) -> 0 | L16: =IF(J16<=0,K16,J16) -> 0 | M16: 0 | N16: =M16*L16 -> 0
A17: =A16+1 -> 4 | K17: =IFERROR(INDEX('Appendix A'!$C$5:$C$42,MATCH('Section 4. Goods and Services'!I17,'Appendix A'!$B$5:$B$42,0)),0) -> 0 | L17: =IF(J17<=0,K17,J17) -> 0 | M17: 0 | N17: =M17*L17 -> 0
A18: =A17+1 -> 5 | K18: =IFERROR(INDEX('Appendix A'!$C$5:$C$42,MATCH('Section 4. Goods and Services'!I18,'Appendix A'!$B$5:$B$42,0)),0) -> 0 | L18: =IF(J18<=0,K18,J18) -> 0 | M18: 0 | N18: =M18*L18 -> 0
A19: =A18+1 -> 6 | K19: =IFERROR(INDEX('Appendix A'!$C$5:$C$42,MATCH('Section 4. Goods and Services'!I19,'Appendix A'!$B$5:$B$42,0)),0) -> 0 | L19: =IF(J19<=0,K19,J19) -> 0 | M19: 0 | N19: =M19*L19 -> 0
A20: =A19+1 -> 7 | K20: =IFERROR(INDEX('Appendix A'!$C$5:$C$42,MATCH('Section 4. Goods and Services'!I20,'Appendix A'!$B$5:$B$42,0)),0) -> 0 | L20: =IF(J20<=0,K20,J20) -> 0 | M20: 0 | N20: =M20*L20 -> 0
A21: =A20+1 -> 8 | K21: =IFERROR(INDEX('Appendix A'!$C$5:$C$42,MATCH('Section 4. Goods and Services'!I21,'Appendix A'!$B$5:$B$42,0)),0) -> 0 | L21: =IF(J21<=0,K21,J21) -> 0 | M21: 0 | N21: =M21*L21 -> 0
A22: =A21+1 -> 9 | K22: =IFERROR(INDEX('Appendix A'!$C$5:$C$42,MATCH('Section 4. Goods and Services'!I22,'Appendix A'!$B$5:$B$42,0)),0) -> 0 | L22: =IF(J22<=0,K22,J22) -> 0 | M22: 0 | N22: =M22*L22 -> 0
A23: =A22+1 -> 10 | K23: =IFERROR(INDEX('Appendix A'!$C$5:$C$42,MATCH('Section 4. Goods and Services'!I23,'Appendix A'!$B$5:$B$42,0)),0) -> 0 | L23: =IF(J23<=0,K23,J23) -> 0 | M23: 0 | N23: =M23*L23 -> 0
A24: =A23+1 -> 11 | K24: =IFERROR(INDEX('Appendix A'!$C$5:$C$42,MATCH('Section 4. Goods and Services'!I24,'Appendix A'!$B$5:$B$42,0)),0) -> 0 | L24: =IF(J24<=0,K24,J24) -> 0 | M24: 0 | N24: =M24*L24 -> 0
A25: =A24+1 -> 12 | K25: =IFERROR(INDEX('Appendix A'!$C$5:$C$42,MATCH('Section 4. Goods and Services'!I25,'Appendix A'!$B$5:$B$42,0)),0) -> 0 | L25: =IF(J25<=0,K25,J25) -> 0 | M25: 0 | N25: =M25*L25 -> 0
A26: =A25+1 -> 13 | K26: =IFERROR(INDEX('Appendix A'!$C$5:$C$42,MATCH('Section 4. Goods and Services'!I26,'Appendix A'!$B$5:$B$42,0)),0) -> 0 | L26: =IF(J26<=0,K26,J26) -> 0 | M26: 0 | N26: =M26*L26 -> 0
... A53: =A52+1 -> 40 | K53: =IFERROR(INDEX('Appendix A'!$C$5:$C$42,MATCH('Section 4. Goods and Services'!I53,'Appendix A'!$B$5:$B$42,0)),0) -> 0 | L53: =IF(J53<=0,K53,J53) -> 0 | M53: 0 | N53: =M53*L53 -> 0
B54: Remaining expenses (SAR) | L54: =IFERROR(SUMPRODUCT($M$14:$M$53,$L$14:$L$53)/SUM($M$14:$M$53),0) -> 0 | M54: =F9-SUM(M14:M53) -> 0 | N54: =M54*L54 -> 0
B55: Total expenses (SAR) | M55: =SUM(M14:M54) -> 0 | N55: =SUM(N14:N54) -> 0
B57: 1. Includes the planned operating expenses and overhead costs of the entity on goods and services during the financial year prior the end of the contract.
B58: 2. List at least 70% or top 40 suppliers of the planned total expenses on Goods and Services in descending order by cost. The entity should contact LCGPA, in order to list more than 40 suppliers.
B59: 3. Supplier's commercial registration number in the Kingdom of Saudi Arabia, and if it is not available, please enter the license number or “not applicable” to indicate that the supplier does not have a commercial registration or license number in the Kingdom of Saudi Arabia.
B60: 4. Enter the supplier's latest audited score or use the sector score of the consumed goods or services.
B61: 5. Planned total expenses refer to the value of total purchases, consumed materials or provided services from suppliers -individually- by the entity during the financial year prior the end of the contract, as per the Guidelines and related instructions.

Sheet Section 5. Capacity Building
B1: Section 5: Capacity Building
B2: Tender Information
B3: Entity Name | C3: =IF('Section 1. General Information'!$C$9:$D$9="","",'Section 1. General Information'!$C$9:$D$9)
B4: ='Section 1. General Information'!B4 -> Tender Name | C4: =IF('Section 1. General Information'!$C$4:$D$4="","",'Section 1. General Information'!$C$4:$D$4)
B5: Contract Start Date (DD/MM/YYYY) | C5: =IF('Section 1. General Information'!$C$5:$D$5="","",'Section 1. General Information'!$C$5:$D$5)
B6: Contract End Date (DD/MM/YYYY) | C6: =IF('Section 1. General Information'!$C$6:$D$6="","",'Section 1. General Information'!$C$6:$D$6)
B8: 5.1 Planned Expenses on Training of Saudis
B9: Expenses during the financial year prior the end of the contract (SAR)1 | C9: 0
B11: 5.2 Planned Expenses on KSA Suppliers Development
B12: Expenses during the financial year prior the end of the contract (SAR)2 | C12: 0
B14: 5.3 Planned Expenses on KSA Research and Development
B15: Expenses during the financial year prior the end of the contract (SAR)3 | C15: 0
B16: Total Revenue during the financial year prior the end of the contract (SAR) | C16: 0
B17: Research and Development Incentive Score (%) | C17: =IFERROR(IF((C15/C16)>=2%,10%,10%*((C15/C16)/2%)),0) -> 0
B19: 1. Planned expenses on the training of Saudi employees during the financial year prior the end of the contract, this includes the cost of trainees and scholarships. Note that the expenses of this section shall not be repeated with other key performance indicators.
B20: 2. Planned expenses on the development of suppliers (who have a Saudi commercial registration number or license number in KSA) during the financial year prior the end of the contract, through training and contribution to enhance suppliers' capabilities. Note that the expenses of this section shall not be repeated with other key performance indicators.
B21: 3. Planned expenses on research and development activities in KSA during the financial year prior the end of the contract. Note that the expenses of this section shall not be repeated with other key performance indicators.

Sheet Section 6. Depreciation & Amor.
B1: Section 6: Depreciation and Amortization
B2: Tender Information
B3: Entity Name | C3: =IF('Section 1. General Information'!$C$9:$D$9="","",'Section 1. General Information'!$C$9:$D$9)
B4: ='Section 1. General Information'!$B$4 -> Tender Name | C4: =IF('Section 1. General Information'!$C$4:$D$4="","",'Section 1. General Information'!$C$4:$D$4)
B5: Contract Start Date (DD/MM/YYYY) | C5: =IF('Section 1. General Information'!$C$5:$D$5="","",'Section 1. General Information'!$C$5:$D$5)
B6: Contract End Date (DD/MM/YYYY) | C6: =IF('Section 1. General Information'!$C$6:$D$6="","",'Section 1. General Information'!$C$6:$D$6)
B8: 6.1 Planned Depreciation and Amortization of Assets during the Financial Year Prior the End of the Contract
B9: Total depreciation and amortization during the financial year prior the end of the contract (SAR) | C9: 0
B11: 6.2 Depreciation and Amortization by Asset class during the Financial Year Prior the End of the Contract
B12: Asset class | C12: Examples of Assets class | D12: Produced in KSA | E12: Planned Depreciation/Amortization (SAR) | F12: Local Content Score (%) | G12: Local Content Contribution (SAR)
A13: 1 | B13: Building and Land Improvements1 | C13: Buildings / Land and Building Improvements | E13: 0 | F13: 1 | G13: =F13*E13 -> 0
A14: =A13+1 -> 2 | B14: Manufactured in KSA - Furniture and Fixtures | C14: Office furniture, desks, cubicles, office chairs | D14: YES | E14: 0 | F14: 1 | G14: =F14*E14 -> 0
A15: =A14+1 -> 3 | B15: Manufactured in KSA - Machinery and Equipment | C15: Industrial equipment, testing equipment, information and communication technology equipment | D15: YES | E15: 0 | F15: 1 | G15: =F15*E15 -> 0
A16: =A15+1 -> 4 | B16: Manufactured in KSA - Vehicles | C16: Mobile cranes, Trucks, vans, cars, trailers, fork lifts | D16: YES | E16: 0 | F16: 1 | G16: =F16*E16 -> 0
A17: =A16+1 -> 5 | B17: Other (please describe) | C17: Other (please give examples) | D17: YES | E17: 0 | F17: 1 | G17: =F17*E17 -> 0
A18: =A17+1 -> 6 | B18: Other (please describe) | C18: Other (please give examples) | D18: YES | E18: 0 | F18: 1 | G18: =F18*E18 -> 0
A19: =A18+1 -> 7 | B19: Other (please describe) | C19: Other (please give examples) | D19: YES | E19: 0 | F19: 1 | G19: =F19*E19 -> 0
A20: =A19+1 -> 8 | B20: Other (please describe) | C20: Other (please give examples) | D20: YES | E20: 0 | F20: 1 | G20: =F20*E20 -> 0
A21: =A20+1 -> 9 | B21: Other (please describe) | C21: Other (please give examples) | D21: YES | E21: 0 | F21: 1 | G21: =F21*E21 -> 0
A22: =A21+1 -> 10 | B22: Other (please describe) | C22: Other (please give examples) | D22: YES | E22: 0 | F22: 1 | G22: =F22*E22 -> 0
A23: =A22+1 -> 11 | B23: Other (please describe) | C23: Other (please give examples) | D23: YES | E23: 0 | F23: 1 | G23: =F23*E23 -> 0
B24: Total depreciation and amortization from foreign Assets | D24: NO | E24: =C9-SUM(E13:E23) -> 0 | F24: 0.3 | G24: =F24*E24 -> 0
B25: Total depreciation and amortization | E25: =SUM(E13:E24) -> 0 | F25: =IFERROR(SUMPRODUCT(F13:F24,E13:E24)/E25,0) -> 0 | G25: =SUM(G13:G24) -> 0
B27: 1. All depreciation related to this category is considered 100% local content as long as they are located in KSA.

Sheet Appendix A
B1: Appendix A
B2: A.1 List of Sector Local Content Scores
B3: General information on Sector Local Content Scores
B4: Sector | C4: Local Content Score (%) | D4: Description | E4: ISIC Code
B5: 1_SERVICES - KSA Accommodation and Facility Rental | C5: 0.6 | D5: The procurement of Services for short-term accommodation (e.g. Hotels) Camping grounds, Other accommodation (e.g. student residences) and rental of office buildings, compounds, warehouses, etc. | E5: 55, 68102
B6: 2_SERVICES - KSA Food and Beverages | C6: 0.4 | D6: The procurement of Services for food and beverages (e.g. Restaurants, catering; the purchase of ready-made food & beverage products is not included) | E6: 56
B7: 3_SERVICES - KSA Industrial Services | C7: 0.36 | D7: The procurement of testing, inspection, certification, calibration, maintenance, blasting, painting, coating and galvanizing services, steam and air conditioning supply | E7: 25921, 33, 35, Exc. 351&352, 38 Exc.381103&383, 712
B8: 4_SERVICES - KSA Security Services | C8: 0.82 | D8: The procurement of security services including guard and patrol services (e.g. Security of facilities) and armored car services, operation of electronic security alarm systems (e.g. fire alarm) | E8: 80, 811001
B9: 5_SERVICES - KSA local Professional Services | C9: 0.5 | D9: The procurement of Professional consulting, Such as engineering, accounting, legal, management consultancy (e.g. strategic, financial planning, budgeting, marketing, policies, HR) | E9: 69-74 Exc. 712
B10: 6_SERVICES - KSA local representative of Foreign professional service provider | C10: 0.2 | D10: The procurement of Professional consulting, Such as engineering, accounting, legal, management consultancy (e.g. strategic, financial planning, budgeting, marketing, policies, HR) provided by a local representative of foreign professional service provider | E10: 69-74 Exc. 712
B11: 7_SERVICES - KSA Real Estate | C11: 0.48 | D11: The procurement of services for selling or buying real estate, providing other real estate services such as appraising real estate or acting as real estate escrow agents. Exc. Facility rental | E11: 68 Exc.68102
B12: 8_SERVICES - KSA Construction | C12: 0.4 | D12: The procurement of construction Services, specialized construction activities for buildings and civil engineering works (e.g., contracting; the procurement of pure construction materials is categorized under Goods sectors), interior and exterior painting of buildings | E12: 41-43
B13: 9_SERVICES - KSA Education | C13: 0.66 | D13: The procurement of all education activities for any profession, oral or written as well as by radio and television or other means of communication (e.g., professional training, language education) | E13: 75, 85
B14: 10_SERVICES - KSA Finance and Insurance | C14: 0.75 | D14: The procurement of all financial Services (e.g., banking, funds management); this category also includes the procurement of insurance and pension Services (e.g., health insurance, transport insurance, accident and fire insurance) | E14: 64-66
B15: 11_SERVICES - KSA Healthcare | C15: 0.38 | D15: The procurement of all Services related to healthcare (the procurement of healthcare equipment and pharmaceuticals is categorized under Goods sectors) | E15: 86-88
B16: 12_SERVICES - KSA Public Administration and Defence | C16: 0.69 | D16: The procurement of Services produced by government bodies (General public administration activities, Foreign affairs, Defense activities, etc.) | E16: 84
B17: 13_SERVICES - KSA Transport and Logistics | C17: 0.45 | D17: The procurement of transport and logistics services from locally based service providers. This sector includes shipping, transportation, cargo services and Saudi based airlines (including freight forward),(Foreign airlines booked by local agency is categorized under foreign service agent),Exc. Rental of cars | E17: 49-53 Exc.49225, 79-7911
B18: 14_SERVICES - KSA Onshore Drilling | C18: 0.3 | D18: The procurement of onshore drilling services | E18: 06, 091
... B30: 26_GOODS - KSA Chemicals & Oil and Gas | C30: 0.61 | D30: The procurement of locally produced chemicals, plastics, manufactured chemical Goods, and Oil & Gas product (e.g. Rubber). | E30: 19-20, 22, 352
B31: 27_GOODS - KSA Chemical Blending | C31: 0.29 | D31: The procurement of locally produced chemicals where the raw material is imported. This sector includes paint manufacturers | E31: 20
B32: 28_GOODS - KSA Machinery and Equipment | C32: 0.25 | D32: The procurement of locally produced machinery and equipment | E32: 265-268, 28 Exc.2813&2814, 29-30
B33: 29_GOODS - KSA Electrical Materials | C33: 0.4 | D33: The procurement of locally produced electrical materials including switch gears, junction boxes, trays, conduits, fixtures, inverters skid and other electrical materials, , Excluding PV panels and electrical inverters. | E33: 27, 2814
B34: 30_GOODS - KSA Mining | C34: 0.45 | D34: The procurement of locally produced raw materials extracted by the mining industry (e.g., coal, metal ores) | E34: 05, 07-08
B35: 31_GOODS - KSA Static Equipment | C35: 0.3 | D35: The procurement of locally produced static equipment such as tanks, pressure vessels and valves (control valves excluded) and steel manufacturers and structural | E35: 24-25 Exc.25114&25921, 2813
B36: 32_GOODS - KSA Cement and Gypsum | C36: 0.5 | D36: The procurement of locally produced cement, concrete and gypsum | E36: 2394-2395
B37: 33_GOODS - KSA Steel Rebar Manufacturing | C37: 0.6 | D37: The procurement of locally produced steel rebar | E37: 25114
B38: 34_GOODS - KSA IT & Telecom Manufacturing | C38: 0.15 | D38: The procurement of manufacturing of computer& electronic components, communication equipment (agents/resellers are not considered) | E38: 261-264
B39: 35_GOODS - KSA Other Manufacturing | C39: 0.3 | D39: The procurement of locally produced paper products, wood products, furniture, secondary raw material, textiles, pharmaceuticals and other industries, Including PV panels and electrical inverters. | E39: 13-18, 21, 23 Exc.2394&2395, 31-32 (Inc. 2790 PV panels and Electrical inverters)
B40: 36_GOODS - KSA Recyclers | C40: 0.7 | D40: The procurement of locally recycled metal scrap, paper, plastic and rubber | E40: 381103, 383
B41: 37_GOODS - KSA Agent or Distributor | C41: 0.05 | D41: The procurement of any kind of Goods from KSA Suppliers who do not produce these Goods; instead, distributors/ traders import and distribute these Goods | E41: 45-47
B42: 38_GOODS - Foreign | C42: 0 | D42: The procurement of Goods from foreign producers, i.e. entities without legal registration in KSA (direct Goods imports) | E42: N /A (supplier type)
